{
  "loggers": [
    {
      "timestamp": "2025-08-20 12:22:33",
      "level": "DEBUG",
      "file": "logging_task.py",
      "line": 136,
      "message": "Configuration loaded",
      "context": {
        "config_file": "settings.json"
      }
    },
    {
      "timestamp": "2025-08-20 12:22:34",
      "level": "INFO",
      "file": "logging_task.py",
      "line": 145,
      "message": "Starting API request to Google Maps",
      "context": {
        "request_params": {
          "source": "home",
          "destination": "work"
        }
      }
    },
    {
      "timestamp": "2025-08-20 12:22:35",
      "level": "INFO",
      "file": "logging_task.py",
      "line": 178,
      "message": "Received response: 200 OK",
      "context": {
        "status_code": 200,
        "response_summary": {
          "status": "OK"
        }
      }
    },
    {
      "timestamp": "2025-08-20 12:22:36",
      "level": "INFO",
      "file": "logging_task.py",
      "line": 202,
      "message": "Database INSERT: travel_times",
      "context": {
        "table": "travel_times",
        "record_id": "home_work",
        "details": {
          "travel_time": "25 minutes",
          "route": "Home to Work"
        }
      }
    },
    {
      "timestamp": "2025-08-20 12:22:37",
      "level": "INFO",
      "file": "logging_task.py",
      "line": 255,
      "message": "Application event: notification_sent",
      "context": {
        "event_type": "notification_sent",
        "details": {
          "channel": "Slack",
          "recipient": "team",
          "message": "Daily travel time updated"
        },
        "timestamp": "2025-08-20T12:22:37.369037"
      }
    },
    {
      "timestamp": "2025-08-20 12:22:38",
      "level": "WARNING",
      "file": "logging_task.py",
      "line": 287,
      "message": "Slack notification delivery delayed",
      "context": {
        "retry_count": 1
      }
    },
    {
      "timestamp": "2025-08-20 12:22:39",
      "level": "ERROR",
      "file": "logging_task.py",
      "line": 301,
      "message": "Failed to calculate result",
      "context": {
        "operation": "division"
      }
    },
    {
      "timestamp": "2025-08-20 12:22:40",
      "level": "ERROR",
      "file": "logging_task.py",
      "line": 302,
      "message": "ZeroDivisionError: division by zero",
      "traceback": [
        "Traceback (most recent call last):",
        "  File \"c:\\Users\\admin\\Documents\\OrbitXO\\examples\\from_almuhannad\\logging_system\\logging_task.py\", line 425, in main",
        "    result = 10 / 0",
        "             ~~~^~~",
        "ZeroDivisionError: division by zero"
      ]
    }
  ]
}
